test_openapi_paths/__init__.py
test_openapi_paths/cli.py
test_openapi_paths/test_PetPath.py
test_openapi_paths/test_PetPathSt.py
test_openapi_paths/test_openapi_paths.py
test_openapi_paths-0.1.4.2.dist-info/AUTHORS.rst
test_openapi_paths-0.1.4.2.dist-info/LICENSE
test_openapi_paths-0.1.4.2.dist-info/METADATA
test_openapi_paths-0.1.4.2.dist-info/WHEEL
test_openapi_paths-0.1.4.2.dist-info/entry_points.txt
test_openapi_paths-0.1.4.2.dist-info/top_level.txt
test_openapi_paths-0.1.4.2.dist-info/RECORD
