Metadata-Version: 2.1
Name: test-openapi-paths
Version: 0.1.4.2
Summary: Tests the paths in an openapi spec
Home-page: https://github.com/lmakuser/test_openapi_paths
Author: Lisa Mak
Author-email: lmak@mitre.org
License: MIT license
Keywords: test_openapi_paths
Platform: UNKNOWN
Classifier: Development Status :: 2 - Pre-Alpha
Classifier: Intended Audience :: Developers
Classifier: License :: OSI Approved :: MIT License
Classifier: Natural Language :: English
Classifier: Programming Language :: Python :: 3
Classifier: Programming Language :: Python :: 3.6
Classifier: Programming Language :: Python :: 3.7
Classifier: Programming Language :: Python :: 3.8
Requires-Python: >=3.6
License-File: LICENSE
License-File: AUTHORS.rst
Requires-Dist: Click (>=7.0)
